python_algerian_mobile_phone_number/AlgerianMobilePhoneNumber.py
python_algerian_mobile_phone_number/__init__.py
python_algerian_mobile_phone_number-0.2.dist-info/LICENSE
python_algerian_mobile_phone_number-0.2.dist-info/METADATA
python_algerian_mobile_phone_number-0.2.dist-info/WHEEL
python_algerian_mobile_phone_number-0.2.dist-info/top_level.txt
python_algerian_mobile_phone_number-0.2.dist-info/RECORD
