Metadata-Version: 2.1
Name: python-algerian-mobile-phone-number
Version: 0.2
Summary: Algerian mobile phone number package
Home-page: https://github.com/mohamine18/python_algerian_mobile_phone_number
Author: Mohammed Amine BOURAS
Author-email: mohamine19@gmail.com
License: UNKNOWN
Platform: UNKNOWN
